john_resume/__init__.py
john_resume-1.0.0.data/scripts/john-resume
john_resume-1.0.0.dist-info/LICENSE
john_resume-1.0.0.dist-info/METADATA
john_resume-1.0.0.dist-info/WHEEL
john_resume-1.0.0.dist-info/top_level.txt
john_resume-1.0.0.dist-info/RECORD
