Metadata-Version: 2.1
Name: john-resume
Version: 1.0.0
Summary: A package for ease of access to the greatest resume available
Home-page: https://github.com/atomfinger/john_resume_pkg
Author: John M. Gundersen
Author-email: john@jmgundersen.com
License: UNKNOWN
Platform: UNKNOWN
Classifier: Programming Language :: Python :: 2.7
Classifier: License :: OSI Approved :: Apache Software License
Classifier: Operating System :: OS Independent
Classifier: Environment :: Console
Classifier: Natural Language :: English
Classifier: Topic :: Other/Nonlisted Topic
Requires-Python: >=2.7
Requires-Dist: requests
